//Methods after sugar removal

        //from static to instance method failed
        Consumer<Integer> consumer = (key) -> System.out.println(key);     
        Consumer<Integer> hot = (key) -> System.out.println(key + "" + this);
        //After desugar method
       private static synthetic lambda$print$0(Ljava/lang/Integer;)V
       private synthetic lambda$print$1(Ljava/lang/Integer;)V

        //change static method params count successful
        String str = "args";
        Consumer<Integer> methodCount1 = (key) -> System.out.println(key);
        Consumer<Integer> methodCount2 = (key) -> System.out.println(key + str);
        private static synthetic lambda$print$2(Ljava/lang/Integer;)V
        private static synthetic lambda$print$3(Ljava/lang/String;Ljava/lang/Integer;)V

        //change instance method params count failed
        Consumer<Integer> instanceCount2 = (key) -> System.out.println(key + "" + this);
        Consumer<Integer> instanceCount3 = (key) -> System.out.println(key + str + this);
        private synthetic lambda$print$4(Ljava/lang/Integer;)V
        private synthetic lambda$print$5(Ljava/lang/String;Ljava/lang/Integer;)V
        
        
        //from nothing add or delete lambd  successful (compile static method)

        //from nothing add or delete lambd  fail (compile instance method)
        Consumer<Integer> instaceMethod = (key) -> System.out.println(this);
        private synthetic lambda$print$6(Ljava/lang/Integer;)V
        hot.accept(1);
        consumer.accept(1);
        
        
        
 ## here is the bytecode 
        
      // class version 52.0 (52)
// access flags 0x21
public class com/jason/Example {

  // compiled from: Example.java
  // access flags 0x19
  public final static INNERCLASS java/lang/invoke/MethodHandles$Lookup java/lang/invoke/MethodHandles Lookup

  // access flags 0x2
  private I x

  // access flags 0x1
  public <init>()V
   L0
    LINENUMBER 5 L0
    ALOAD 0
    INVOKESPECIAL java/lang/Object.<init> ()V
    RETURN
   L1
    LOCALVARIABLE this Lcom/jason/Example; L0 L1 0
    MAXSTACK = 1
    MAXLOCALS = 1

  // access flags 0x1
  public print(I)V
   L0
    LINENUMBER 12 L0
    INVOKEDYNAMIC accept()Ljava/util/function/Consumer; [
      // handle kind 0x6 : INVOKESTATIC
      java/lang/invoke/LambdaMetafactory.metafactory(Ljava/lang/invoke/MethodHandles$Lookup;Ljava/lang/String;Ljava/lang/invoke/MethodType;Ljava/lang/invoke/MethodType;Ljava/lang/invoke/MethodHandle;Ljava/lang/invoke/MethodType;)Ljava/lang/invoke/CallSite;
      // arguments:
      (Ljava/lang/Object;)V, 
      // handle kind 0x6 : INVOKESTATIC
      com/jason/Example.lambda$print$0(Ljava/lang/Integer;)V, 
      (Ljava/lang/Integer;)V
    ]
    ASTORE 2
   L1
    LINENUMBER 13 L1
    ALOAD 0
    INVOKEDYNAMIC accept(Lcom/jason/Example;)Ljava/util/function/Consumer; [
      // handle kind 0x6 : INVOKESTATIC
      java/lang/invoke/LambdaMetafactory.metafactory(Ljava/lang/invoke/MethodHandles$Lookup;Ljava/lang/String;Ljava/lang/invoke/MethodType;Ljava/lang/invoke/MethodType;Ljava/lang/invoke/MethodHandle;Ljava/lang/invoke/MethodType;)Ljava/lang/invoke/CallSite;
      // arguments:
      (Ljava/lang/Object;)V, 
      // handle kind 0x7 : INVOKESPECIAL
      com/jason/Example.lambda$print$1(Ljava/lang/Integer;)V, 
      (Ljava/lang/Integer;)V
    ]
    ASTORE 3
   L2
    LINENUMBER 16 L2
    LDC "args"
    ASTORE 4
   L3
    LINENUMBER 17 L3
    INVOKEDYNAMIC accept()Ljava/util/function/Consumer; [
      // handle kind 0x6 : INVOKESTATIC
      java/lang/invoke/LambdaMetafactory.metafactory(Ljava/lang/invoke/MethodHandles$Lookup;Ljava/lang/String;Ljava/lang/invoke/MethodType;Ljava/lang/invoke/MethodType;Ljava/lang/invoke/MethodHandle;Ljava/lang/invoke/MethodType;)Ljava/lang/invoke/CallSite;
      // arguments:
      (Ljava/lang/Object;)V, 
      // handle kind 0x6 : INVOKESTATIC
      com/jason/Example.lambda$print$2(Ljava/lang/Integer;)V, 
      (Ljava/lang/Integer;)V
    ]
    ASTORE 5
   L4
    LINENUMBER 18 L4
    ALOAD 4
    INVOKEDYNAMIC accept(Ljava/lang/String;)Ljava/util/function/Consumer; [
      // handle kind 0x6 : INVOKESTATIC
      java/lang/invoke/LambdaMetafactory.metafactory(Ljava/lang/invoke/MethodHandles$Lookup;Ljava/lang/String;Ljava/lang/invoke/MethodType;Ljava/lang/invoke/MethodType;Ljava/lang/invoke/MethodHandle;Ljava/lang/invoke/MethodType;)Ljava/lang/invoke/CallSite;
      // arguments:
      (Ljava/lang/Object;)V, 
      // handle kind 0x6 : INVOKESTATIC
      com/jason/Example.lambda$print$3(Ljava/lang/String;Ljava/lang/Integer;)V, 
      (Ljava/lang/Integer;)V
    ]
    ASTORE 6
   L5
    LINENUMBER 21 L5
    ALOAD 0
    INVOKEDYNAMIC accept(Lcom/jason/Example;)Ljava/util/function/Consumer; [
      // handle kind 0x6 : INVOKESTATIC
      java/lang/invoke/LambdaMetafactory.metafactory(Ljava/lang/invoke/MethodHandles$Lookup;Ljava/lang/String;Ljava/lang/invoke/MethodType;Ljava/lang/invoke/MethodType;Ljava/lang/invoke/MethodHandle;Ljava/lang/invoke/MethodType;)Ljava/lang/invoke/CallSite;
      // arguments:
      (Ljava/lang/Object;)V, 
      // handle kind 0x7 : INVOKESPECIAL
      com/jason/Example.lambda$print$4(Ljava/lang/Integer;)V, 
      (Ljava/lang/Integer;)V
    ]
    ASTORE 7
   L6
    LINENUMBER 22 L6
    ALOAD 0
    ALOAD 4
    INVOKEDYNAMIC accept(Lcom/jason/Example;Ljava/lang/String;)Ljava/util/function/Consumer; [
      // handle kind 0x6 : INVOKESTATIC
      java/lang/invoke/LambdaMetafactory.metafactory(Ljava/lang/invoke/MethodHandles$Lookup;Ljava/lang/String;Ljava/lang/invoke/MethodType;Ljava/lang/invoke/MethodType;Ljava/lang/invoke/MethodHandle;Ljava/lang/invoke/MethodType;)Ljava/lang/invoke/CallSite;
      // arguments:
      (Ljava/lang/Object;)V, 
      // handle kind 0x7 : INVOKESPECIAL
      com/jason/Example.lambda$print$5(Ljava/lang/String;Ljava/lang/Integer;)V, 
      (Ljava/lang/Integer;)V
    ]
    ASTORE 8
   L7
    LINENUMBER 27 L7
    ALOAD 0
    INVOKEDYNAMIC accept(Lcom/jason/Example;)Ljava/util/function/Consumer; [
      // handle kind 0x6 : INVOKESTATIC
      java/lang/invoke/LambdaMetafactory.metafactory(Ljava/lang/invoke/MethodHandles$Lookup;Ljava/lang/String;Ljava/lang/invoke/MethodType;Ljava/lang/invoke/MethodType;Ljava/lang/invoke/MethodHandle;Ljava/lang/invoke/MethodType;)Ljava/lang/invoke/CallSite;
      // arguments:
      (Ljava/lang/Object;)V, 
      // handle kind 0x7 : INVOKESPECIAL
      com/jason/Example.lambda$print$6(Ljava/lang/Integer;)V, 
      (Ljava/lang/Integer;)V
    ]
    ASTORE 9
   L8
    LINENUMBER 28 L8
    ALOAD 3
    ICONST_1
    INVOKESTATIC java/lang/Integer.valueOf (I)Ljava/lang/Integer;
    INVOKEINTERFACE java/util/function/Consumer.accept (Ljava/lang/Object;)V (itf)
   L9
    LINENUMBER 29 L9
    ALOAD 2
    ICONST_1
    INVOKESTATIC java/lang/Integer.valueOf (I)Ljava/lang/Integer;
    INVOKEINTERFACE java/util/function/Consumer.accept (Ljava/lang/Object;)V (itf)
   L10
    LINENUMBER 30 L10
    RETURN
   L11
    LOCALVARIABLE this Lcom/jason/Example; L0 L11 0
    LOCALVARIABLE y I L0 L11 1
    LOCALVARIABLE consumer Ljava/util/function/Consumer; L1 L11 2
    // signature Ljava/util/function/Consumer<Ljava/lang/Integer;>;
    // declaration: consumer extends java.util.function.Consumer<java.lang.Integer>
    LOCALVARIABLE hot Ljava/util/function/Consumer; L2 L11 3
    // signature Ljava/util/function/Consumer<Ljava/lang/Integer;>;
    // declaration: hot extends java.util.function.Consumer<java.lang.Integer>
    LOCALVARIABLE str Ljava/lang/String; L3 L11 4
    LOCALVARIABLE methodCount1 Ljava/util/function/Consumer; L4 L11 5
    // signature Ljava/util/function/Consumer<Ljava/lang/Integer;>;
    // declaration: methodCount1 extends java.util.function.Consumer<java.lang.Integer>
    LOCALVARIABLE methodCount2 Ljava/util/function/Consumer; L5 L11 6
    // signature Ljava/util/function/Consumer<Ljava/lang/Integer;>;
    // declaration: methodCount2 extends java.util.function.Consumer<java.lang.Integer>
    LOCALVARIABLE instanceCount2 Ljava/util/function/Consumer; L6 L11 7
    // signature Ljava/util/function/Consumer<Ljava/lang/Integer;>;
    // declaration: instanceCount2 extends java.util.function.Consumer<java.lang.Integer>
    LOCALVARIABLE instanceCount3 Ljava/util/function/Consumer; L7 L11 8
    // signature Ljava/util/function/Consumer<Ljava/lang/Integer;>;
    // declaration: instanceCount3 extends java.util.function.Consumer<java.lang.Integer>
    LOCALVARIABLE instaceMethod Ljava/util/function/Consumer; L8 L11 9
    // signature Ljava/util/function/Consumer<Ljava/lang/Integer;>;
    // declaration: instaceMethod extends java.util.function.Consumer<java.lang.Integer>
    MAXSTACK = 2
    MAXLOCALS = 10

  // access flags 0x1002
  private synthetic lambda$print$6(Ljava/lang/Integer;)V
   L0
    LINENUMBER 27 L0
    GETSTATIC java/lang/System.out : Ljava/io/PrintStream;
    ALOAD 0
    INVOKEVIRTUAL java/io/PrintStream.println (Ljava/lang/Object;)V
    RETURN
   L1
    LOCALVARIABLE this Lcom/jason/Example; L0 L1 0
    LOCALVARIABLE key Ljava/lang/Integer; L0 L1 1
    MAXSTACK = 2
    MAXLOCALS = 2

  // access flags 0x1002
  private synthetic lambda$print$5(Ljava/lang/String;Ljava/lang/Integer;)V
   L0
    LINENUMBER 22 L0
    GETSTATIC java/lang/System.out : Ljava/io/PrintStream;
    NEW java/lang/StringBuilder
    DUP
    INVOKESPECIAL java/lang/StringBuilder.<init> ()V
    ALOAD 2
    INVOKEVIRTUAL java/lang/StringBuilder.append (Ljava/lang/Object;)Ljava/lang/StringBuilder;
    ALOAD 1
    INVOKEVIRTUAL java/lang/StringBuilder.append (Ljava/lang/String;)Ljava/lang/StringBuilder;
    ALOAD 0
    INVOKEVIRTUAL java/lang/StringBuilder.append (Ljava/lang/Object;)Ljava/lang/StringBuilder;
    INVOKEVIRTUAL java/lang/StringBuilder.toString ()Ljava/lang/String;
    INVOKEVIRTUAL java/io/PrintStream.println (Ljava/lang/String;)V
    RETURN
   L1
    LOCALVARIABLE this Lcom/jason/Example; L0 L1 0
    LOCALVARIABLE str Ljava/lang/String; L0 L1 1
    LOCALVARIABLE key Ljava/lang/Integer; L0 L1 2
    MAXSTACK = 3
    MAXLOCALS = 3

  // access flags 0x1002
  private synthetic lambda$print$4(Ljava/lang/Integer;)V
   L0
    LINENUMBER 21 L0
    GETSTATIC java/lang/System.out : Ljava/io/PrintStream;
    NEW java/lang/StringBuilder
    DUP
    INVOKESPECIAL java/lang/StringBuilder.<init> ()V
    ALOAD 1
    INVOKEVIRTUAL java/lang/StringBuilder.append (Ljava/lang/Object;)Ljava/lang/StringBuilder;
    LDC ""
    INVOKEVIRTUAL java/lang/StringBuilder.append (Ljava/lang/String;)Ljava/lang/StringBuilder;
    ALOAD 0
    INVOKEVIRTUAL java/lang/StringBuilder.append (Ljava/lang/Object;)Ljava/lang/StringBuilder;
    INVOKEVIRTUAL java/lang/StringBuilder.toString ()Ljava/lang/String;
    INVOKEVIRTUAL java/io/PrintStream.println (Ljava/lang/String;)V
    RETURN
   L1
    LOCALVARIABLE this Lcom/jason/Example; L0 L1 0
    LOCALVARIABLE key Ljava/lang/Integer; L0 L1 1
    MAXSTACK = 3
    MAXLOCALS = 2

  // access flags 0x100A
  private static synthetic lambda$print$3(Ljava/lang/String;Ljava/lang/Integer;)V
   L0
    LINENUMBER 18 L0
    GETSTATIC java/lang/System.out : Ljava/io/PrintStream;
    NEW java/lang/StringBuilder
    DUP
    INVOKESPECIAL java/lang/StringBuilder.<init> ()V
    ALOAD 1
    INVOKEVIRTUAL java/lang/StringBuilder.append (Ljava/lang/Object;)Ljava/lang/StringBuilder;
    ALOAD 0
    INVOKEVIRTUAL java/lang/StringBuilder.append (Ljava/lang/String;)Ljava/lang/StringBuilder;
    INVOKEVIRTUAL java/lang/StringBuilder.toString ()Ljava/lang/String;
    INVOKEVIRTUAL java/io/PrintStream.println (Ljava/lang/String;)V
    RETURN
   L1
    LOCALVARIABLE str Ljava/lang/String; L0 L1 0
    LOCALVARIABLE key Ljava/lang/Integer; L0 L1 1
    MAXSTACK = 3
    MAXLOCALS = 2

  // access flags 0x100A
  private static synthetic lambda$print$2(Ljava/lang/Integer;)V
   L0
    LINENUMBER 17 L0
    GETSTATIC java/lang/System.out : Ljava/io/PrintStream;
    LDC "s"
    INVOKEVIRTUAL java/io/PrintStream.println (Ljava/lang/String;)V
    RETURN
   L1
    LOCALVARIABLE key Ljava/lang/Integer; L0 L1 0
    MAXSTACK = 2
    MAXLOCALS = 1

  // access flags 0x1002
  private synthetic lambda$print$1(Ljava/lang/Integer;)V
   L0
    LINENUMBER 13 L0
    GETSTATIC java/lang/System.out : Ljava/io/PrintStream;
    NEW java/lang/StringBuilder
    DUP
    INVOKESPECIAL java/lang/StringBuilder.<init> ()V
    ALOAD 1
    INVOKEVIRTUAL java/lang/StringBuilder.append (Ljava/lang/Object;)Ljava/lang/StringBuilder;
    LDC ""
    INVOKEVIRTUAL java/lang/StringBuilder.append (Ljava/lang/String;)Ljava/lang/StringBuilder;
    ALOAD 0
    INVOKEVIRTUAL java/lang/StringBuilder.append (Ljava/lang/Object;)Ljava/lang/StringBuilder;
    INVOKEVIRTUAL java/lang/StringBuilder.toString ()Ljava/lang/String;
    INVOKEVIRTUAL java/io/PrintStream.println (Ljava/lang/String;)V
    RETURN
   L1
    LOCALVARIABLE this Lcom/jason/Example; L0 L1 0
    LOCALVARIABLE key Ljava/lang/Integer; L0 L1 1
    MAXSTACK = 3
    MAXLOCALS = 2

  // access flags 0x100A
  private static synthetic lambda$print$0(Ljava/lang/Integer;)V
   L0
    LINENUMBER 12 L0
    GETSTATIC java/lang/System.out : Ljava/io/PrintStream;
    ALOAD 0
    INVOKEVIRTUAL java/io/PrintStream.println (Ljava/lang/Object;)V
    RETURN
   L1
    LOCALVARIABLE key Ljava/lang/Integer; L0 L1 0
    MAXSTACK = 2
    MAXLOCALS = 1
}

        
        
